labcli/base.py
labcli/cli.py
labcli/version.py
labcli/utils/containerlab_utils.py
labcli/utils/docker_utils.py
labcli-0.2.0.dist-info/METADATA
labcli-0.2.0.dist-info/WHEEL
labcli-0.2.0.dist-info/entry_points.txt
labcli-0.2.0.dist-info/licenses/LICENSE
labcli-0.2.0.dist-info/RECORD
