Metadata-Version: 2.3
Name: labcli
Version: 0.2.0
Summary: Add your description here
License-File: LICENSE
Requires-Python: >=3.10
Requires-Dist: python-dotenv>=1.0.1
Requires-Dist: typer>=0.12.5
